[{"id":1,"maker":"Chevrolet","model":"Sportvan G20","year":1993},
{"id":2,"maker":"Jeep","model":"Patriot","year":2007},
{"id":3,"maker":"Ferrari","model":"612 Scaglietti","year":2008},
{"id":4,"maker":"Ford","model":"Thunderbird","year":1995},
{"id":5,"maker":"GMC","model":"Canyon","year":2012},
{"id":6,"maker":"Volvo","model":"V70","year":2009},
{"id":7,"maker":"Suzuki","model":"Grand Vitara","year":2010},
{"id":8,"maker":"Ford","model":"Escort","year":1990},
{"id":9,"maker":"Toyota","model":"Yaris","year":2009},
{"id":10,"maker":"Infiniti","model":"M","year":2003}]